example_package/__init__.py
example_package/example.py
pkg1/__init__.py
pkg1/pkg1.txt
pkg2/__init__.py
pkg2/data/otherdata.dat
pkg2/data/somefile.dat
timmins/__init__.py
timmins/__main__.py
timmins/aaa.py
example_pkg_jych720_2_0-0.0.10.dist-info/LICENSE
example_pkg_jych720_2_0-0.0.10.dist-info/METADATA
example_pkg_jych720_2_0-0.0.10.dist-info/WHEEL
example_pkg_jych720_2_0-0.0.10.dist-info/entry_points.txt
example_pkg_jych720_2_0-0.0.10.dist-info/top_level.txt
example_pkg_jych720_2_0-0.0.10.dist-info/RECORD
