Metadata-Version: 2.1
Name: example-pkg-jych720-2-0
Version: 0.0.10
Summary: setuptools tutorial
Home-page: http://www.xmetal.com
Author: jych720_2
Author-email: jych720_2@hotmail.com
License: UNKNOWN
Platform: UNKNOWN
Classifier: Programming Language :: Python :: 3
Classifier: License :: OSI Approved :: MIT License
Classifier: Operating System :: OS Independent
Requires-Python: >=3.6
License-File: LICENSE
Requires-Dist: pywin32 (>=1.0) ; platform_system == "Windows"
